README.rst
setup.cfg
setup.py
validoot/__init__.py
validoot/builtins.py
validoot/clauses.py
validoot/decorators.py
validoot/exceptions.py
validoot/operations.py
validoot.egg-info/PKG-INFO
validoot.egg-info/SOURCES.txt
validoot.egg-info/dependency_links.txt
validoot.egg-info/requires.txt
validoot.egg-info/top_level.txt