Metadata-Version: 1.1
Name: validoot
Version: 1.2
Summary: Simple validation for function arguments using a decorator.
Home-page: http://github.com/AstromechZA/validoot
Author: Ben Meier
Author-email: benmeier@fastmail.com
License: MIT
Download-URL: https://github.com/AstromechZA/validoot/tarball/1.2
Keywords: validate,function arguments,decorator
Platform: UNKNOWN
Classifier: Intended Audience :: Developers
Classifier: License :: OSI Approved :: MIT License
Classifier: Programming Language :: Python :: 2
Classifier: Programming Language :: Python :: 3
Classifier: Topic :: Software Development
